[
{
    "model": "cars.car",
    "pk": 1,
    "fields": {
        "car_title": "2017 Ferrari 488 GTB",
        "state": "CA",
        "city": "Los Angeles",
        "color": "White",
        "model": "488 GTB",
        "year": 2018,
        "condition": "Used",
        "price": 60000,
        "description": "<p>The&nbsp;<strong>Ferrari 488</strong>&nbsp;(Type F142M) is a&nbsp;<a href=\"https://en.wikipedia.org/wiki/Rear_mid-engine,_rear-wheel_drive_layout\" title=\"Rear mid-engine, rear-wheel drive layout\">mid-engine</a>&nbsp;<a href=\"https://en.wikipedia.org/wiki/Sports_car\" title=\"Sports car\">sports car</a>&nbsp;produced by the Italian automobile manufacturer&nbsp;<a href=\"https://en.wikipedia.org/wiki/Ferrari\" title=\"Ferrari\">Ferrari</a>. The car replaced the&nbsp;<a href=\"https://en.wikipedia.org/wiki/Ferrari_458\" title=\"Ferrari 458\">458</a>, being the first mid-engine Ferrari to use a turbocharged V8 since the&nbsp;<a href=\"https://en.wikipedia.org/wiki/Ferrari_F40\" title=\"Ferrari F40\">F40</a>.</p>\r\n\r\n<p>The car is powered by a 3.9-litre&nbsp;<a href=\"https://en.wikipedia.org/wiki/Twin-turbocharged\" title=\"Twin-turbocharged\">twin-turbocharged</a>&nbsp;<a href=\"https://en.wikipedia.org/wiki/V8_engine\" title=\"V8 engine\">V8 engine</a>, smaller in displacement but generating a higher power output than the 458&#39;s&nbsp;<a href=\"https://en.wikipedia.org/wiki/Naturally_aspirated_engine\" title=\"Naturally aspirated engine\">naturally aspirated engine</a>. The 488 GTB was named &quot;The Supercar of the Year 2015&quot; by car magazine&nbsp;<a href=\"https://en.wikipedia.org/wiki/Top_Gear_(magazine)\" title=\"Top Gear (magazine)\"><em>Top Gear</em></a>, as well as becoming&nbsp;<em><a href=\"https://en.wikipedia.org/wiki/Motor_Trend\" title=\"Motor Trend\">Motor Trend</a></em>&#39;s 2017 &quot;Best Driver&#39;s Car&quot;.<a href=\"https://en.wikipedia.org/wiki/Ferrari_488#cite_note-7\">[7]</a>&nbsp;<a href=\"https://en.wikipedia.org/wiki/Jeremy_Clarkson\" title=\"Jeremy Clarkson\">Jeremy Clarkson</a>&nbsp;announced the 488 Pista as his 2019 Supercar of the Year.<a href=\"https://en.wikipedia.org/wiki/Ferrari_488#cite_note-8\">[8]</a>&nbsp;The 488 was succeeded by the&nbsp;<a href=\"https://en.wikipedia.org/wiki/Ferrari_F8_Tributo\" title=\"Ferrari F8 Tributo\">F8 Tributo</a>&nbsp;in February 2019.</p>",
        "car_photo": "photos/2021/01/10/1902536891.jpg",
        "car_photo_1": "photos/2021/01/10/1902536917.jpg",
        "car_photo_2": "photos/2021/01/10/1902537043.jpg",
        "car_photo_3": "photos/2021/01/10/1902537077.jpg",
        "car_photo_4": "photos/2021/01/10/1902537082.jpg",
        "features": "Audio Interface,Airbags,Air Conditioning,Alarm System,Direct Fuel Injection,Wind Deflector",
        "body_style": "Sport",
        "engine": "3.4L Mid-Engine V6",
        "transmission": "Automatic",
        "interior": "Grey",
        "miles": 10000,
        "doors": "2",
        "passengers": 2,
        "vin_no": "WP0AB2E81EK1788547",
        "milage": 5,
        "fuel_type": "Petrol",
        "no_of_owners": "1",
        "is_featured": true,
        "created_date": "2021-01-10T10:18:57Z"
    }
},
{
    "model": "cars.car",
    "pk": 2,
    "fields": {
        "car_title": "2017 Ford Edge",
        "state": "TX",
        "city": "Dallas",
        "color": "Black",
        "model": "Edge",
        "year": 2017,
        "condition": "Used",
        "price": 25000,
        "description": "<p>The&nbsp;<strong>Ford Edge</strong>&nbsp;is a range of&nbsp;<a href=\"https://en.wikipedia.org/wiki/Crossover_SUV\" title=\"Crossover SUV\">crossover SUVs</a>&nbsp;manufactured by the&nbsp;<a href=\"https://en.wikipedia.org/wiki/Ford_Motor_Company\" title=\"Ford Motor Company\">Ford Motor Company</a>. Introduced for the 2007 model year, the Edge is the first&nbsp;<a href=\"https://en.wikipedia.org/wiki/Crossover_(automobile)\" title=\"Crossover (automobile)\">CUV</a>&nbsp;marketed by Ford in North America; the model line is currently in its second generation. Deriving its name from a trim package of the&nbsp;<a href=\"https://en.wikipedia.org/wiki/Ford_Ranger_(Americas)\" title=\"Ford Ranger (Americas)\">Ford Ranger</a>, the Ford Edge is slotted between the&nbsp;<a href=\"https://en.wikipedia.org/wiki/Ford_Escape\" title=\"Ford Escape\">Ford Escape</a>&nbsp;and the&nbsp;<a href=\"https://en.wikipedia.org/wiki/Ford_Explorer\" title=\"Ford Explorer\">Ford Explorer</a>&nbsp;within the Ford product line.</p>\r\n\r\n<p>Sharing its underpinnings with the&nbsp;<a href=\"https://en.wikipedia.org/wiki/Ford_Fusion_(Americas)\" title=\"Ford Fusion (Americas)\">Ford Fusion sedan</a>, Ford has also produced the model line as the&nbsp;<a href=\"https://en.wikipedia.org/wiki/Lincoln_MKX\" title=\"Lincoln MKX\">Lincoln MKX</a>&nbsp;(since 2019, the Lincoln Nautilus); the first generation was also produced as the&nbsp;<a href=\"https://en.wikipedia.org/wiki/Mazda_CX-9\" title=\"Mazda CX-9\">Mazda CX-9</a>. The second-generation is also marketed by&nbsp;<a href=\"https://en.wikipedia.org/wiki/Ford_of_Europe\" title=\"Ford of Europe\">Ford of Europe</a>, slotted between the Kuga (Escape) and the Explorer PHEV.</p>",
        "car_photo": "photos/2021/01/10/1901478607.jpg",
        "car_photo_1": "photos/2021/01/10/1901478618.jpg",
        "car_photo_2": "photos/2021/01/10/1901478646.jpg",
        "car_photo_3": "photos/2021/01/10/1901478672.jpg",
        "car_photo_4": "photos/2021/01/10/1901478687.jpg",
        "features": "Cruise Control,Audio Interface,Air Conditioning,Power Steering,Direct Fuel Injection,Auto Start/Stop",
        "body_style": "SUV",
        "engine": "3.4L Mid-Engine V7",
        "transmission": "Automatic",
        "interior": "Grey",
        "miles": 15000,
        "doors": "4",
        "passengers": 5,
        "vin_no": "WP0AYH31EK1788547",
        "milage": 8,
        "fuel_type": "Petrol",
        "no_of_owners": "2",
        "is_featured": true,
        "created_date": "2021-01-10T10:20:21Z"
    }
},
{
    "model": "cars.car",
    "pk": 3,
    "fields": {
        "car_title": "2017 Ford F-250 Super Duty",
        "state": "MN",
        "city": "Minnepolis",
        "color": "Black",
        "model": "F-250",
        "year": 2018,
        "condition": "Used",
        "price": 25000,
        "description": "<p>The&nbsp;<strong>Ford Super Duty</strong>&nbsp;(short for F-Series Super Duty) is a series of trucks manufactured by&nbsp;<a href=\"https://en.wikipedia.org/wiki/Ford_Motor_Company\" title=\"Ford Motor Company\">Ford Motor Company</a>. Introduced in 1998 for the 1999 model year, the F-Series Super Duty trucks marked the addition of a heavy-duty pickup to the&nbsp;<a href=\"https://en.wikipedia.org/wiki/Ford_F-Series\" title=\"Ford F-Series\">Ford F-Series</a>&nbsp;range with the new versions of the F-250, F-350, and F-450 pickups, while the previous 1987&ndash;1997 F-Super Duty&nbsp;<a href=\"https://en.wikipedia.org/wiki/Chassis_cab\" title=\"Chassis cab\">chassis cabs</a>&nbsp;were replaced by the F-450 chassis cab and F-550 Super Duty.</p>\r\n\r\n<p>The Super Duty trucks utilize a distinct chassis from the lighter&nbsp;<a href=\"https://en.wikipedia.org/wiki/F-150\" title=\"F-150\">F-150</a>, with heavier-duty chassis and suspension components to allow for higher payload and towing capacities; additionally, the product line continued the use of&nbsp;<a href=\"https://en.wikipedia.org/wiki/Ford_Power_Stroke_engine\" title=\"Ford Power Stroke engine\">Ford PowerStroke</a>&nbsp;diesel engines. With a&nbsp;<a href=\"https://en.wikipedia.org/wiki/Gross_vehicle_weight_rating\" title=\"Gross vehicle weight rating\">GVWR</a>&nbsp;over 8,500&nbsp;lb (3,900&nbsp;kg), Super Duty pickups are&nbsp;<a href=\"https://en.wikipedia.org/wiki/Truck_classification\" title=\"Truck classification\">class 2 and 3</a>&nbsp;trucks while chassis cab trucks are class 4 and class 5. The F-Series Super Duty has been used as the base chassis of the&nbsp;<a href=\"https://en.wikipedia.org/wiki/Ford_Excursion\" title=\"Ford Excursion\">Ford Excursion</a>&nbsp;full-size SUV.</p>",
        "car_photo": "photos/2021/01/10/1894300894.jpg",
        "car_photo_1": "photos/2021/01/10/1894300905.jpg",
        "car_photo_2": "photos/2021/01/10/1894300920.jpg",
        "car_photo_3": "photos/2021/01/10/1900155012.jpg",
        "car_photo_4": "photos/2021/01/10/1900155133.jpg",
        "features": "Cruise Control,Airbags,Air Conditioning,Power Steering,Reversing Camera,Wind Deflector",
        "body_style": "SUV",
        "engine": "3.4L Mid-Engine V7",
        "transmission": "Automatic",
        "interior": "Grey",
        "miles": 13000,
        "doors": "4",
        "passengers": 5,
        "vin_no": "WP0DS2E81EK1788547",
        "milage": 10,
        "fuel_type": "Diesel",
        "no_of_owners": "1",
        "is_featured": false,
        "created_date": "2021-01-10T10:24:09Z"
    }
},
{
    "model": "cars.car",
    "pk": 4,
    "fields": {
        "car_title": "2017 Jaguar F-PACE",
        "state": "NY",
        "city": "New York",
        "color": "Dark Green",
        "model": "F-PACE",
        "year": 2016,
        "condition": "Used",
        "price": 40000,
        "description": "<p>The&nbsp;<strong>Jaguar F-Pace</strong>&nbsp;(X761) is a&nbsp;<a href=\"https://en.wikipedia.org/wiki/Compact_executive_car\" title=\"Compact executive car\">compact luxury</a>&nbsp;<a href=\"https://en.wikipedia.org/wiki/Crossover_SUV\" title=\"Crossover SUV\">crossover SUV</a>&nbsp;made by British&nbsp;<a href=\"https://en.wikipedia.org/wiki/Automaker\" title=\"Automaker\">car manufacturer</a>&nbsp;<a href=\"https://en.wikipedia.org/wiki/Jaguar_Land_Rover\" title=\"Jaguar Land Rover\">Jaguar Land Rover</a>&nbsp;under their&nbsp;<a href=\"https://en.wikipedia.org/wiki/Jaguar_Cars\" title=\"Jaguar Cars\">Jaguar marque</a>, the first model to be built by Jaguar in the crossover SUV class. It was formally announced at the&nbsp;<a href=\"https://en.wikipedia.org/wiki/North_American_International_Auto_Show#2015\" title=\"North American International Auto Show\">2015 North American International Auto Show</a>&nbsp;in Detroit, with sales commencing in 2016 following an unveiling at the&nbsp;<a href=\"https://en.wikipedia.org/wiki/International_Motor_Show_Germany#2015\" title=\"International Motor Show Germany\">International Motor Show Germany</a>&nbsp;in Frankfurt in September 2015.<a href=\"https://en.wikipedia.org/wiki/Jaguar_F-Pace#cite_note-4\">[4]</a>&nbsp;The design of the F-Pace is based on the 2013&nbsp;<a href=\"https://en.wikipedia.org/wiki/Jaguar_C-X17\" title=\"Jaguar C-X17\">Jaguar C-X17</a>&nbsp;concept car.<a href=\"https://en.wikipedia.org/wiki/Jaguar_F-Pace#cite_note-BBC_News_120115-5\">[5]</a>&nbsp;The 2017 Jaguar F-PACE has been named the honorary winner of the 2017 World Car of the Year and World Car Design of the Year Awards at the&nbsp;<a href=\"https://en.wikipedia.org/wiki/New_York_International_Auto_Show\" title=\"New York International Auto Show\">New York International Auto Show</a>.<a href=\"https://en.wikipedia.org/wiki/Jaguar_F-Pace#cite_note-6\">[6]</a></p>",
        "car_photo": "photos/2021/01/10/1902932503.jpg",
        "car_photo_1": "photos/2021/01/10/1902932514.jpg",
        "car_photo_2": "photos/2021/01/10/1902932528.jpg",
        "car_photo_3": "photos/2021/01/10/1902932542.jpg",
        "car_photo_4": "",
        "features": "Cruise Control,Audio Interface,Airbags,ParkAssist,Auto Start/Stop,Bluetooth Handset",
        "body_style": "SUV",
        "engine": "3.4L Mid-Engine V5",
        "transmission": "Automatic",
        "interior": "Black",
        "miles": 12500,
        "doors": "5",
        "passengers": 5,
        "vin_no": "WP0AYH31EK17881232",
        "milage": 7,
        "fuel_type": "Petrol",
        "no_of_owners": "1",
        "is_featured": true,
        "created_date": "2021-01-10T10:27:45Z"
    }
},
{
    "model": "cars.car",
    "pk": 5,
    "fields": {
        "car_title": "2018 Toyota 4Runner",
        "state": "CA",
        "city": "San Fransisco",
        "color": "Silver",
        "model": "4Runner",
        "year": 2015,
        "condition": "Used",
        "price": 15000,
        "description": "<p>The&nbsp;<strong>Toyota 4Runner</strong>&nbsp;is a compact, later mid-size&nbsp;<a href=\"https://en.wikipedia.org/wiki/Sport_utility_vehicle\" title=\"Sport utility vehicle\">sport utility vehicle</a>&nbsp;produced by the Japanese manufacturer&nbsp;<a href=\"https://en.wikipedia.org/wiki/Toyota\" title=\"Toyota\">Toyota</a>&nbsp;and sold throughout the world from 1984 to present. In Japan, it is known as the&nbsp;<strong>Toyota Hilux Surf</strong>&nbsp;(Japanese: \u30c8\u30e8\u30bf\u30fb\u30cf\u30a4\u30e9\u30c3\u30af\u30b9\u30b5\u30fc\u30d5,&nbsp;<em>Toyota Hairakkusus\u0101fu</em>)&nbsp;which was withdrawn from the market in 2009. The original 4Runner was a&nbsp;<a href=\"https://en.wikipedia.org/wiki/Compact_SUV\" title=\"Compact SUV\">compact SUV</a>&nbsp;and little more than a Toyota pickup truck with a fiberglass shell over the bed, but the model has since undergone significant independent development into a cross between a compact and a mid-size SUV. All 4Runners have been built in Japan at Toyota&#39;s&nbsp;<a href=\"https://en.wikipedia.org/wiki/Tahara_plant\" title=\"Tahara plant\">plant</a>&nbsp;in&nbsp;<a href=\"https://en.wikipedia.org/wiki/Tahara,_Aichi\" title=\"Tahara, Aichi\">Tahara, Aichi</a>, or at the&nbsp;<a href=\"https://en.wikipedia.org/wiki/Hino_Motors\" title=\"Hino Motors\">Hino Motors</a>&nbsp;(a Toyota subsidiary) plant in&nbsp;<a href=\"https://en.wikipedia.org/wiki/Hamura\" title=\"Hamura\">Hamura</a>.</p>\r\n\r\n<p>For Southeast Asia the Hilux Surf was replaced in 2005 by the similar&nbsp;<a href=\"https://en.wikipedia.org/wiki/Toyota_Fortuner\" title=\"Toyota Fortuner\">Fortuner</a>, which is based on the Hilux platform.</p>\r\n\r\n<p>As of 2014, the 4Runner is sold in the United States, Bolivia, Canada, Central America, Bahamas, Ecuador, Peru, Chile and Venezuela.</p>",
        "car_photo": "photos/2021/01/10/1893633875.jpg",
        "car_photo_1": "photos/2021/01/10/1893633879.jpg",
        "car_photo_2": "photos/2021/01/10/1893633884.jpg",
        "car_photo_3": "photos/2021/01/10/1896836883.jpg",
        "car_photo_4": "photos/2021/01/10/1896836887.jpg",
        "features": "Airbags,Air Conditioning,Alarm System,Power Steering,Direct Fuel Injection,Wind Deflector",
        "body_style": "SUV",
        "engine": "3.4L Mid-Engine V6",
        "transmission": "Automatic",
        "interior": "Black",
        "miles": 60000,
        "doors": "5",
        "passengers": 5,
        "vin_no": "WP0AB2E81EK1712452",
        "milage": 5,
        "fuel_type": "Petrol",
        "no_of_owners": "3",
        "is_featured": false,
        "created_date": "2021-01-10T14:35:56Z"
    }
},
{
    "model": "cars.car",
    "pk": 6,
    "fields": {
        "car_title": "2018 Toyota Corolla",
        "state": "KY",
        "city": "Lexinton",
        "color": "White",
        "model": "Corolla",
        "year": 2019,
        "condition": "Used",
        "price": 20000,
        "description": "<p>The&nbsp;<strong>Toyota Corolla</strong>&nbsp;(Japanese: \u30c8\u30e8\u30bf\u30fb\u30ab\u30ed\u30fc\u30e9,&nbsp;<em>Toyota Kar\u014dra</em>)&nbsp;is a line of&nbsp;<a href=\"https://en.wikipedia.org/wiki/Subcompact_car\" title=\"Subcompact car\">subcompact</a>&nbsp;and&nbsp;<a href=\"https://en.wikipedia.org/wiki/Compact_car\" title=\"Compact car\">compact cars</a>&nbsp;manufactured by&nbsp;<a href=\"https://en.wikipedia.org/wiki/Toyota\" title=\"Toyota\">Toyota</a>. Introduced in 1966, the Corolla was the best-selling car worldwide by 1974 and has been one of the best-selling cars in the world since then. In 1997, the Corolla became the&nbsp;<a href=\"https://en.wikipedia.org/wiki/List_of_automobile_sales_by_model\" title=\"List of automobile sales by model\">best selling nameplate in the world</a>, surpassing the&nbsp;<a href=\"https://en.wikipedia.org/wiki/Volkswagen_Beetle\" title=\"Volkswagen Beetle\">Volkswagen Beetle</a>.<a href=\"https://en.wikipedia.org/wiki/Toyota_Corolla#cite_note-1\">[1]</a>&nbsp;Toyota reached the milestone of 44 million Corollas sold over twelve generations in 2016.<a href=\"https://en.wikipedia.org/wiki/Toyota_Corolla#cite_note-44million-2\">[2]</a>&nbsp;The series has undergone several major redesigns.</p>\r\n\r\n<p>The name&nbsp;<em><a href=\"https://en.wikipedia.org/wiki/Corolla_(headgear)\" title=\"Corolla (headgear)\">Corolla</a></em>&nbsp;is part of Toyota&#39;s naming tradition of using names derived from the&nbsp;<a href=\"https://en.wikipedia.org/wiki/Toyota_Crown\" title=\"Toyota Crown\">Toyota Crown</a>&nbsp;for sedans, with&nbsp;<em>&quot;<a href=\"https://en.wiktionary.org/wiki/corolla\" title=\"wikt:corolla\">corolla</a>&quot;</em>&nbsp;<a href=\"https://en.wikipedia.org/wiki/Latin\" title=\"Latin\">Latin</a>&nbsp;for &quot;small crown&quot;.<a href=\"https://en.wikipedia.org/wiki/Toyota_Corolla#cite_note-3\">[3]</a>&nbsp;The Corolla has always been exclusive in Japan to&nbsp;<em><a href=\"https://en.wikipedia.org/wiki/Toyota_Netz\" title=\"Toyota Netz\">Toyota Corolla Store</a></em>&nbsp;locations, and manufactured in Japan with a twin, called the&nbsp;<a href=\"https://en.wikipedia.org/wiki/Toyota_Sprinter\" title=\"Toyota Sprinter\">Toyota Sprinter</a>&nbsp;until 2000. From 2006 to 2018 in Japan and much of the world, and from 2018 to 2020 in Taiwan, the hatchback companion had been called the&nbsp;<a href=\"https://en.wikipedia.org/wiki/Toyota_Auris\" title=\"Toyota Auris\">Toyota Auris</a>.</p>\r\n\r\n<p>Early models were mostly&nbsp;<a href=\"https://en.wikipedia.org/wiki/Rear-wheel_drive\" title=\"Rear-wheel drive\">rear-wheel drive</a>, while later models have been&nbsp;<a href=\"https://en.wikipedia.org/wiki/Front-wheel_drive\" title=\"Front-wheel drive\">front-wheel drive</a>.&nbsp;<a href=\"https://en.wikipedia.org/wiki/Four-wheel_drive\" title=\"Four-wheel drive\">Four-wheel drive</a>&nbsp;versions have also been produced. The Corolla&#39;s traditional competitors have been the&nbsp;<a href=\"https://en.wikipedia.org/wiki/Nissan_Sunny\" title=\"Nissan Sunny\">Nissan Sunny</a>, introduced the same year as the Corolla in Japan and the later&nbsp;<a href=\"https://en.wikipedia.org/wiki/Honda_Civic\" title=\"Honda Civic\">Honda Civic</a>&nbsp;and&nbsp;<a href=\"https://en.wikipedia.org/wiki/Mitsubishi_Lancer\" title=\"Mitsubishi Lancer\">Mitsubishi Lancer</a>. The Corolla&#39;s chassis designation code is &quot;E&quot;, as described in Toyota&#39;s chassis and engine codes.</p>",
        "car_photo": "photos/2021/01/10/1900893299.jpg",
        "car_photo_1": "photos/2021/01/10/1900893311.jpg",
        "car_photo_2": "photos/2021/01/10/1900893319.jpg",
        "car_photo_3": "photos/2021/01/10/1900893329.jpg",
        "car_photo_4": "photos/2021/01/10/1900893391.jpg",
        "features": "Cruise Control,Audio Interface,Airbags,Air Conditioning,ParkAssist,Reversing Camera,Bluetooth Handset",
        "body_style": "Compact",
        "engine": "3.4L Mid-Engine V5",
        "transmission": "Automatic",
        "interior": "Black",
        "miles": 20000,
        "doors": "5",
        "passengers": 4,
        "vin_no": "WP0DS2E81EK1788325",
        "milage": 2,
        "fuel_type": "Petrol",
        "no_of_owners": "1",
        "is_featured": true,
        "created_date": "2021-01-10T14:39:50Z"
    }
},
{
    "model": "pages.team",
    "pk": 2,
    "fields": {
        "first_name": "Martin",
        "last_name": "Smith",
        "designation": "Founder",
        "photo": "photos/2021/01/10/avatar-11.jpg",
        "facebook_link": "https://facebook.com",
        "twitter_link": "https://twitter.com",
        "google_plus_link": "https://google.com",
        "created_date": "2021-01-10T06:37:22.775Z"
    }
},
{
    "model": "pages.team",
    "pk": 3,
    "fields": {
        "first_name": "Stone",
        "last_name": "Carolyn",
        "designation": "Creative Director",
        "photo": "photos/2021/01/10/avatar-9.jpg",
        "facebook_link": "https://facebook.com",
        "twitter_link": "https://twitter.com",
        "google_plus_link": "https://google.com",
        "created_date": "2021-01-10T06:38:08.833Z"
    }
},
{
    "model": "pages.team",
    "pk": 4,
    "fields": {
        "first_name": "Brandon",
        "last_name": "Miller",
        "designation": "Co-Founder",
        "photo": "photos/2021/01/10/avatar-1.jpg",
        "facebook_link": "https://facebook.com",
        "twitter_link": "https://twitter.com",
        "google_plus_link": "https://google.com",
        "created_date": "2021-01-10T06:38:43.754Z"
    }
},
{
    "model": "pages.team",
    "pk": 5,
    "fields": {
        "first_name": "John",
        "last_name": "Doe",
        "designation": "CEO",
        "photo": "photos/2021/01/10/avatar-12.jpg",
        "facebook_link": "https://facebook.com",
        "twitter_link": "https://twitter.com",
        "google_plus_link": "https://google.com",
        "created_date": "2021-01-10T06:39:35.801Z"
    }
},
{
    "model": "pages.team",
    "pk": 6,
    "fields": {
        "first_name": "Michelle",
        "last_name": "Nelson",
        "designation": "Support Manager",
        "photo": "photos/2021/01/10/avatar-10.jpg",
        "facebook_link": "https://facebook.com",
        "twitter_link": "https://twitter.com",
        "google_plus_link": "https://google.com",
        "created_date": "2021-01-10T06:40:09.481Z"
    }
},
{
    "model": "contacts.contact",
    "pk": 1,
    "fields": {
        "first_name": "Yue",
        "last_name": "Jia",
        "car_id": 6,
        "customer_need": "I'm interested in this",
        "car_title": "2018 Toyota Corolla",
        "city": "Los Angeles",
        "state": "California",
        "email": "superjiayue@126.com",
        "phone": "13076062381",
        "message": "That's cool",
        "user_id": 1,
        "create_date": "2021-01-11T10:24:33.853Z"
    }
},
{
    "model": "contacts.contact",
    "pk": 2,
    "fields": {
        "first_name": "Yue",
        "last_name": "Jia",
        "car_id": 1,
        "customer_need": "I'd like to know your best price for this",
        "car_title": "2017 Ferrari 488 GTB",
        "city": "Lexinton",
        "state": "Kentucky",
        "email": "superjiayue@126.com",
        "phone": "13076062381",
        "message": "I love this car. Could you give me for free?",
        "user_id": 1,
        "create_date": "2021-01-11T10:29:44.312Z"
    }
},
{
    "model": "contacts.contact",
    "pk": 3,
    "fields": {
        "first_name": "Root",
        "last_name": "Shaw",
        "car_id": 5,
        "customer_need": "I'm interested in this",
        "car_title": "2018 Toyota 4Runner",
        "city": "Lexinton",
        "state": "Kentucky",
        "email": "shaw@gmail.com",
        "phone": "",
        "message": "Hahaha",
        "user_id": 2,
        "create_date": "2021-01-11T10:39:15.113Z"
    }
},
{
    "model": "contacts.contact",
    "pk": 4,
    "fields": {
        "first_name": "Root",
        "last_name": "Shaw",
        "car_id": 4,
        "customer_need": "I'm interested in this",
        "car_title": "2017 Jaguar F-PACE",
        "city": "New York",
        "state": "New York",
        "email": "shaw@gmail.com",
        "phone": "",
        "message": "Good car!",
        "user_id": 2,
        "create_date": "2021-01-11T10:58:40.709Z"
    }
},
{
    "model": "contacts.contact",
    "pk": 5,
    "fields": {
        "first_name": "Root",
        "last_name": "Shaw",
        "car_id": 2,
        "customer_need": "I'm interested in this",
        "car_title": "2017 Ford Edge",
        "city": "Los Angeles",
        "state": "California",
        "email": "shaw@gmail.com",
        "phone": "",
        "message": "2333",
        "user_id": 2,
        "create_date": "2021-01-11T11:00:53.657Z"
    }
},
{
    "model": "auth.user",
    "fields": {
        "password": "pbkdf2_sha256$180000$R5hK1I5sS1K4$juZnCjNXgA4SsP+Jw2BiGOVJMwK44T0xhAOBVDwcaO0=",
        "last_login": "2021-01-11T09:49:18Z",
        "is_superuser": true,
        "username": "djangoadmin",
        "first_name": "Root",
        "last_name": "Jia",
        "email": "superjiayue@126.com",
        "is_staff": true,
        "is_active": true,
        "date_joined": "2021-01-09T14:17:24Z",
        "groups": [],
        "user_permissions": []
    }
},
{
    "model": "auth.user",
    "fields": {
        "password": "pbkdf2_sha256$180000$m1JN4shAX0p9$J2VFk12JiJ4plZGad6cjsKQgoIW8ZwTLf42td7pPxzE=",
        "last_login": "2021-01-11T12:14:18.125Z",
        "is_superuser": false,
        "username": "Shaw",
        "first_name": "Root",
        "last_name": "Shaw",
        "email": "shaw@gmail.com",
        "is_staff": false,
        "is_active": true,
        "date_joined": "2021-01-11T06:56:54.572Z",
        "groups": [],
        "user_permissions": []
    }
},
{
    "model": "auth.user",
    "fields": {
        "password": "!mGpBsviX4UlrXLAIKuFzgAojFx71KHWeVBzqBSJv",
        "last_login": "2021-01-11T08:54:11.766Z",
        "is_superuser": false,
        "username": "root",
        "first_name": "Root",
        "last_name": "Jia",
        "email": "",
        "is_staff": false,
        "is_active": true,
        "date_joined": "2021-01-11T08:54:11.734Z",
        "groups": [],
        "user_permissions": []
    }
},
{
    "model": "sessions.session",
    "pk": "ngym1eq3x30vb2593cn2jtlkbr1r64jy",
    "fields": {
        "session_data": "NDhmZWZhZDhmNDE3YjRiZDI0NzRmZjc3YTlkYTQ5MDg0MzAwNzI1Nzp7Il9hdXRoX3VzZXJfaWQiOiIyIiwiX2F1dGhfdXNlcl9iYWNrZW5kIjoiZGphbmdvLmNvbnRyaWIuYXV0aC5iYWNrZW5kcy5Nb2RlbEJhY2tlbmQiLCJfYXV0aF91c2VyX2hhc2giOiI3MWQxNWVkZDU2YmVkN2IzODM2YjY3OWJkY2I4OTg5MDFkOWRlN2NlIn0=",
        "expire_date": "2021-01-25T12:14:18.127Z"
    }
},
{
    "model": "sessions.session",
    "pk": "x1ow1256ulipqiwhi5rsbvy97mozpif5",
    "fields": {
        "session_data": "Y2NjNTJkYmEyMmFlYzgzZmNlMzZlODQxN2E0ZGQxNjE4NmZkNDM0Yjp7Il9hdXRoX3VzZXJfaWQiOiIxIiwiX2F1dGhfdXNlcl9iYWNrZW5kIjoiZGphbmdvLmNvbnRyaWIuYXV0aC5iYWNrZW5kcy5Nb2RlbEJhY2tlbmQiLCJfYXV0aF91c2VyX2hhc2giOiI5MThiYTkyOTU4ZDNmOTM4NTY4MTllOGE1NTU1ZGUyZjkyNDg2Y2JlIn0=",
        "expire_date": "2021-01-25T08:32:59.780Z"
    }
},
{
    "model": "sites.site",
    "fields": {
        "domain": "localhost:8000",
        "name": "localhost:8000"
    }
},
{
    "model": "socialaccount.socialapp",
    "pk": 1,
    "fields": {
        "provider": "facebook",
        "name": "Facebook login",
        "client_id": "990618511466541",
        "secret": "93554ccca08778ca229cc724a2e8932f",
        "key": "",
        "sites": [
            [
                "localhost:8000"
            ]
        ]
    }
},
{
    "model": "socialaccount.socialapp",
    "pk": 2,
    "fields": {
        "provider": "google",
        "name": "Google Login",
        "client_id": "230771861758-2eh1k1anqtssclq11lavkrqbrknmhu85.apps.googleusercontent.com",
        "secret": "JpO1J-mN1kXN-EOO2CSp5Dio",
        "key": "",
        "sites": [
            [
                "localhost:8000"
            ]
        ]
    }
},
{
    "model": "socialaccount.socialaccount",
    "pk": 1,
    "fields": {
        "user": [
            "root"
        ],
        "provider": "google",
        "uid": "101919423790788930377",
        "last_login": "2021-01-11T08:54:11.746Z",
        "date_joined": "2021-01-11T08:54:11.747Z",
        "extra_data": "{\"id\": \"101919423790788930377\", \"name\": \"Root Jia\", \"given_name\": \"Root\", \"family_name\": \"Jia\", \"picture\": \"https://lh6.googleusercontent.com/-6rw5O_cLdYQ/AAAAAAAAAAI/AAAAAAAAAAA/AMZuucmSyifnUJ5kb2-W-srBzlInCWoLVQ/s96-c/photo.jpg\", \"locale\": \"zh-CN\"}"
    }
},
{
    "model": "socialaccount.socialtoken",
    "pk": 1,
    "fields": {
        "app": 2,
        "account": 1,
        "token": "ya29.a0AfH6SMAbW7_ry9D3GuRdcIy7Gl-X_tANXAlDbFUIgbGW0OXppIQ4iteU_3yYQUTZp6X3PIzVeIvziHCFbHIeM2mmJUyneCBJwhZ8R6asUaRNLSnfafK2xj0pYW3Up2taL8hPq-1c6_mkij57wy2d5vsSbM-OK2Zx2zoj-g6mUlU",
        "token_secret": "",
        "expires_at": "2021-01-11T09:54:10.038Z"
    }
},
{
    "model": "admin.logentry",
    "pk": 1,
    "fields": {
        "action_time": "2021-01-10T05:59:02.584Z",
        "user": [
            "djangoadmin"
        ],
        "content_type": [
            "auth",
            "user"
        ],
        "object_id": "1",
        "object_repr": "djangoadmin",
        "action_flag": 2,
        "change_message": "[{\"changed\": {\"fields\": [\"Username\", \"First name\", \"Last name\"]}}]"
    }
},
{
    "model": "admin.logentry",
    "pk": 2,
    "fields": {
        "action_time": "2021-01-10T06:19:16.911Z",
        "user": [
            "djangoadmin"
        ],
        "content_type": [
            "pages",
            "team"
        ],
        "object_id": "1",
        "object_repr": "Team object (1)",
        "action_flag": 1,
        "change_message": "[{\"added\": {}}]"
    }
},
{
    "model": "admin.logentry",
    "pk": 3,
    "fields": {
        "action_time": "2021-01-10T06:35:10.560Z",
        "user": [
            "djangoadmin"
        ],
        "content_type": [
            "pages",
            "team"
        ],
        "object_id": "1",
        "object_repr": "Carmen",
        "action_flag": 2,
        "change_message": "[{\"changed\": {\"fields\": [\"Photo\"]}}]"
    }
},
{
    "model": "admin.logentry",
    "pk": 4,
    "fields": {
        "action_time": "2021-01-10T06:36:22.155Z",
        "user": [
            "djangoadmin"
        ],
        "content_type": [
            "pages",
            "team"
        ],
        "object_id": "1",
        "object_repr": "Carmen",
        "action_flag": 3,
        "change_message": ""
    }
},
{
    "model": "admin.logentry",
    "pk": 5,
    "fields": {
        "action_time": "2021-01-10T06:37:22.776Z",
        "user": [
            "djangoadmin"
        ],
        "content_type": [
            "pages",
            "team"
        ],
        "object_id": "2",
        "object_repr": "Martin",
        "action_flag": 1,
        "change_message": "[{\"added\": {}}]"
    }
},
{
    "model": "admin.logentry",
    "pk": 6,
    "fields": {
        "action_time": "2021-01-10T06:38:08.835Z",
        "user": [
            "djangoadmin"
        ],
        "content_type": [
            "pages",
            "team"
        ],
        "object_id": "3",
        "object_repr": "Stone",
        "action_flag": 1,
        "change_message": "[{\"added\": {}}]"
    }
},
{
    "model": "admin.logentry",
    "pk": 7,
    "fields": {
        "action_time": "2021-01-10T06:38:43.756Z",
        "user": [
            "djangoadmin"
        ],
        "content_type": [
            "pages",
            "team"
        ],
        "object_id": "4",
        "object_repr": "Brandon",
        "action_flag": 1,
        "change_message": "[{\"added\": {}}]"
    }
},
{
    "model": "admin.logentry",
    "pk": 8,
    "fields": {
        "action_time": "2021-01-10T06:39:35.803Z",
        "user": [
            "djangoadmin"
        ],
        "content_type": [
            "pages",
            "team"
        ],
        "object_id": "5",
        "object_repr": "John",
        "action_flag": 1,
        "change_message": "[{\"added\": {}}]"
    }
},
{
    "model": "admin.logentry",
    "pk": 9,
    "fields": {
        "action_time": "2021-01-10T06:40:09.483Z",
        "user": [
            "djangoadmin"
        ],
        "content_type": [
            "pages",
            "team"
        ],
        "object_id": "6",
        "object_repr": "Michelle",
        "action_flag": 1,
        "change_message": "[{\"added\": {}}]"
    }
},
{
    "model": "admin.logentry",
    "pk": 10,
    "fields": {
        "action_time": "2021-01-10T10:20:10.336Z",
        "user": [
            "djangoadmin"
        ],
        "content_type": [
            "cars",
            "car"
        ],
        "object_id": "1",
        "object_repr": "Car object (1)",
        "action_flag": 1,
        "change_message": "[{\"added\": {}}]"
    }
},
{
    "model": "admin.logentry",
    "pk": 11,
    "fields": {
        "action_time": "2021-01-10T10:24:07.455Z",
        "user": [
            "djangoadmin"
        ],
        "content_type": [
            "cars",
            "car"
        ],
        "object_id": "2",
        "object_repr": "Car object (2)",
        "action_flag": 1,
        "change_message": "[{\"added\": {}}]"
    }
},
{
    "model": "admin.logentry",
    "pk": 12,
    "fields": {
        "action_time": "2021-01-10T10:27:41.094Z",
        "user": [
            "djangoadmin"
        ],
        "content_type": [
            "cars",
            "car"
        ],
        "object_id": "3",
        "object_repr": "Car object (3)",
        "action_flag": 1,
        "change_message": "[{\"added\": {}}]"
    }
},
{
    "model": "admin.logentry",
    "pk": 13,
    "fields": {
        "action_time": "2021-01-10T10:32:22.259Z",
        "user": [
            "djangoadmin"
        ],
        "content_type": [
            "cars",
            "car"
        ],
        "object_id": "4",
        "object_repr": "Car object (4)",
        "action_flag": 1,
        "change_message": "[{\"added\": {}}]"
    }
},
{
    "model": "admin.logentry",
    "pk": 14,
    "fields": {
        "action_time": "2021-01-10T10:56:16.100Z",
        "user": [
            "djangoadmin"
        ],
        "content_type": [
            "cars",
            "car"
        ],
        "object_id": "3",
        "object_repr": "2017 Ford F-250 Super Duty",
        "action_flag": 2,
        "change_message": "[{\"changed\": {\"fields\": [\"Is featured\"]}}]"
    }
},
{
    "model": "admin.logentry",
    "pk": 15,
    "fields": {
        "action_time": "2021-01-10T12:21:55.776Z",
        "user": [
            "djangoadmin"
        ],
        "content_type": [
            "cars",
            "car"
        ],
        "object_id": "1",
        "object_repr": "2017 Ferrari 488 GTB",
        "action_flag": 2,
        "change_message": "[{\"changed\": {\"fields\": [\"Price\"]}}]"
    }
},
{
    "model": "admin.logentry",
    "pk": 16,
    "fields": {
        "action_time": "2021-01-10T14:39:47.882Z",
        "user": [
            "djangoadmin"
        ],
        "content_type": [
            "cars",
            "car"
        ],
        "object_id": "5",
        "object_repr": "2018 Toyota 4Runner",
        "action_flag": 1,
        "change_message": "[{\"added\": {}}]"
    }
},
{
    "model": "admin.logentry",
    "pk": 17,
    "fields": {
        "action_time": "2021-01-10T14:44:40.040Z",
        "user": [
            "djangoadmin"
        ],
        "content_type": [
            "cars",
            "car"
        ],
        "object_id": "6",
        "object_repr": "2018 Toyota Corolla",
        "action_flag": 1,
        "change_message": "[{\"added\": {}}]"
    }
},
{
    "model": "admin.logentry",
    "pk": 18,
    "fields": {
        "action_time": "2021-01-11T08:25:59.132Z",
        "user": [
            "djangoadmin"
        ],
        "content_type": [
            "socialaccount",
            "socialapp"
        ],
        "object_id": "1",
        "object_repr": "Facebook login",
        "action_flag": 1,
        "change_message": "[{\"added\": {}}]"
    }
},
{
    "model": "admin.logentry",
    "pk": 19,
    "fields": {
        "action_time": "2021-01-11T08:27:02.696Z",
        "user": [
            "djangoadmin"
        ],
        "content_type": [
            "sites",
            "site"
        ],
        "object_id": "1",
        "object_repr": "localhost:8000",
        "action_flag": 2,
        "change_message": "[{\"changed\": {\"fields\": [\"Domain name\", \"Display name\"]}}]"
    }
},
{
    "model": "admin.logentry",
    "pk": 20,
    "fields": {
        "action_time": "2021-01-11T08:50:27.948Z",
        "user": [
            "djangoadmin"
        ],
        "content_type": [
            "socialaccount",
            "socialapp"
        ],
        "object_id": "2",
        "object_repr": "Google Login",
        "action_flag": 1,
        "change_message": "[{\"added\": {}}]"
    }
},
{
    "model": "admin.logentry",
    "pk": 21,
    "fields": {
        "action_time": "2021-01-11T10:59:33.245Z",
        "user": [
            "djangoadmin"
        ],
        "content_type": [
            "auth",
            "user"
        ],
        "object_id": "1",
        "object_repr": "djangoadmin",
        "action_flag": 2,
        "change_message": "[{\"changed\": {\"fields\": [\"Email address\"]}}]"
    }
},
{
    "model": "admin.logentry",
    "pk": 22,
    "fields": {
        "action_time": "2021-01-11T11:46:48.077Z",
        "user": [
            "djangoadmin"
        ],
        "content_type": [
            "auth",
            "user"
        ],
        "object_id": "1",
        "object_repr": "djangoadmin",
        "action_flag": 2,
        "change_message": "[{\"changed\": {\"fields\": [\"Email address\"]}}]"
    }
}
]
